LICENSE
README.rst
pyproject.toml
setup.py
netorca_sdk/__init__.py
netorca_sdk/auth.py
netorca_sdk/config.py
netorca_sdk/consumer.py
netorca_sdk/exceptions.py
netorca_sdk/junit_reporter.py
netorca_sdk/netorca.py
netorca_sdk/serviceowner.py
netorca_sdk/validations.py
netorca_sdk.egg-info/PKG-INFO
netorca_sdk.egg-info/SOURCES.txt
netorca_sdk.egg-info/dependency_links.txt
netorca_sdk.egg-info/requires.txt
netorca_sdk.egg-info/top_level.txt
tests/test_auth.py
tests/test_consumer.py
tests/test_junit.py
tests/test_netorca.py
tests/test_serviceowner.py