Metadata-Version: 2.4
Name: netorca-sdk
Version: 0.3.0
Summary: A package for interacting with the NetOrca API
Home-page: https://gitlab.com/netorca_public/netorca_sdk/
Author: Scott Rowlandson
Author-email: scott@netautomate.org
License: MIT
Keywords: netorca,orchestration,netautomate
Classifier: Development Status :: 5 - Production/Stable
Classifier: Intended Audience :: Developers
Classifier: Topic :: Software Development :: Build Tools
Classifier: License :: OSI Approved :: MIT License
Classifier: Programming Language :: Python :: 3.8
Classifier: Programming Language :: Python :: 3.9
Classifier: Programming Language :: Python :: 3.10
Classifier: Programming Language :: Python :: 3.11
Classifier: Programming Language :: Python :: 3.12
Requires-Python: >=3.8
License-File: LICENSE
Requires-Dist: beautifultable
Requires-Dist: ruamel.yaml
Requires-Dist: requests
Requires-Dist: gitpython
Dynamic: author
Dynamic: author-email
Dynamic: classifier
Dynamic: description
Dynamic: description-content-type
Dynamic: home-page
Dynamic: keywords
Dynamic: license
Dynamic: license-file
Dynamic: requires-dist
Dynamic: requires-python
Dynamic: summary
